tablequiz/__init__.py
tablequiz/main.py
tablequiz/py.typed
tablequiz/quiz.py
tablequiz/serialization.py
tablequiz/server.py
tablequiz/statics/reset.css
tablequiz/statics/reveal.css
tablequiz/statics/reveal.esm.js
tablequiz/statics/reveal.esm.js.map
tablequiz/statics/reveal.js
tablequiz/statics/reveal.js.map
tablequiz/statics/tablequiz.css
tablequiz/statics/plugin/highlight/highlight.esm.js
tablequiz/statics/plugin/highlight/highlight.js
tablequiz/statics/plugin/highlight/monokai.css
tablequiz/statics/plugin/highlight/plugin.js
tablequiz/statics/plugin/highlight/zenburn.css
tablequiz/statics/plugin/markdown/markdown.esm.js
tablequiz/statics/plugin/markdown/markdown.js
tablequiz/statics/plugin/markdown/plugin.js
tablequiz/statics/plugin/math/katex.js
tablequiz/statics/plugin/math/math.esm.js
tablequiz/statics/plugin/math/math.js
tablequiz/statics/plugin/math/mathjax2.js
tablequiz/statics/plugin/math/mathjax3.js
tablequiz/statics/plugin/math/plugin.js
tablequiz/statics/plugin/notes/notes.esm.js
tablequiz/statics/plugin/notes/notes.js
tablequiz/statics/plugin/notes/plugin.js
tablequiz/statics/plugin/notes/speaker-view.html
tablequiz/statics/plugin/search/plugin.js
tablequiz/statics/plugin/search/search.esm.js
tablequiz/statics/plugin/search/search.js
tablequiz/statics/plugin/zoom/plugin.js
tablequiz/statics/plugin/zoom/zoom.esm.js
tablequiz/statics/plugin/zoom/zoom.js
tablequiz/statics/theme/beige.css
tablequiz/statics/theme/black-contrast.css
tablequiz/statics/theme/black.css
tablequiz/statics/theme/blood.css
tablequiz/statics/theme/dracula.css
tablequiz/statics/theme/league.css
tablequiz/statics/theme/moon.css
tablequiz/statics/theme/night.css
tablequiz/statics/theme/serif.css
tablequiz/statics/theme/simple.css
tablequiz/statics/theme/sky.css
tablequiz/statics/theme/solarized.css
tablequiz/statics/theme/white-contrast.css
tablequiz/statics/theme/white.css
tablequiz/statics/theme/white_contrast_compact_verbatim_headers.css
tablequiz-0.1.3.dist-info/METADATA
tablequiz-0.1.3.dist-info/WHEEL
tablequiz-0.1.3.dist-info/entry_points.txt
tablequiz-0.1.3.dist-info/RECORD
